pyjion/__init__.py
pyjion/__init__.pyi
pyjion/__main__.py
pyjion/_pyjion.cp310-win_amd64.pyd
pyjion/absint.cpp
pyjion/absint.h
pyjion/absvalue.cpp
pyjion/absvalue.h
pyjion/attrtable.cpp
pyjion/attrtable.h
pyjion/base.cpp
pyjion/base.h
pyjion/binarycomp.cpp
pyjion/block.h
pyjion/cee.h
pyjion/codemodel.cpp
pyjion/codemodel.h
pyjion/cowvector.h
pyjion/crossplat.h
pyjion/dis.py
pyjion/exceptionhandling.cpp
pyjion/exceptionhandling.h
pyjion/exceptions.h
pyjion/flags.h
pyjion/frame.h
pyjion/ilgen.h
pyjion/instructions.cpp
pyjion/instructions.h
pyjion/intrins.cpp
pyjion/intrins.h
pyjion/ipycomp.h
pyjion/jitinfo.h
pyjion/jitinit.cpp
pyjion/jitinit.h
pyjion/knownmethods.h
pyjion/pgc.cpp
pyjion/pycomp.cpp
pyjion/pycomp.h
pyjion/pyjit.cpp
pyjion/pyjit.h
pyjion/stack.cpp
pyjion/stack.h
pyjion/types.h
pyjion/unboxing.cpp
pyjion/unboxing.h
pyjion/util.h
pyjion/wsgi.py
pyjion/compat/malloc.h
pyjion/objects/unboxedrangeobject.cpp
pyjion/objects/unboxedrangeobject.h
pyjion-2.0.0.data/data/.dockerignore
pyjion-2.0.0.data/data/CHANGELOG.md
pyjion-2.0.0.data/data/CODE_OF_CONDUCT.md
pyjion-2.0.0.data/data/Dockerfile
pyjion-2.0.0.data/data/LICENSE.md
pyjion-2.0.0.data/data/README.md
pyjion-2.0.0.data/data/pyproject.toml
pyjion-2.0.0.data/data/setup.py
pyjion-2.0.0.dist-info/LICENSE.md
pyjion-2.0.0.dist-info/METADATA
pyjion-2.0.0.dist-info/WHEEL
pyjion-2.0.0.dist-info/entry_points.txt
pyjion-2.0.0.dist-info/top_level.txt
pyjion-2.0.0.dist-info/RECORD
