Metadata-Version: 2.1
Name: pyjion
Version: 2.0.0
Summary: A JIT compiler wrapper for CPython
Home-page: https://www.trypyjion.com/
Author: Anthony Shaw
Author-email: anthonyshaw@apache.org
License: MIT
Project-URL: Documentation, https://pyjion.readthedocs.io/
Project-URL: Repository, https://github.com/tonybaloney/Pyjion
Classifier: Development Status :: 4 - Beta
Classifier: Programming Language :: Python :: 3
Classifier: License :: OSI Approved :: MIT License
Classifier: Operating System :: OS Independent
Requires-Python: ==3.10.*
License-File: LICENSE.md
Provides-Extra: dis
Requires-Dist: rich (>=11.0) ; extra == 'dis'
Requires-Dist: distorm3 ; extra == 'dis'
